MANIFEST.in
setup.cfg
setup.py
solent/__init__.py
solent/cpair.py
solent/keycode.py
solent/paths.py
solent.egg-info/PKG-INFO
solent.egg-info/SOURCES.txt
solent.egg-info/dependency_links.txt
solent.egg-info/top_level.txt
solent/base/__init__.py
solent/base/interface_script.py
solent/base/liblog.py
solent/base/libtest.py
solent/base/mempool.py
solent/base/rail_line_finder.py
solent/base/ref.py
solent/base/sip.py
solent/base/small.py
solent/console/__init__.py
solent/console/cgrid.py
solent/console/iconsole.py
solent/console/keystream.py
solent/console/rail_menu.py
solent/console/curses/__init__.py
solent/console/curses/curses_console.py
solent/console/pygame/__init__.py
solent/console/pygame/pygame_console.py
solent/console/windows/__init__.py
solent/console/windows/windows_console.py
solent/demo/__init__.py
solent/demo/draw.py
solent/demo/snake.py
solent/demo/weeds.py
solent/draft/__init__.py
solent/draft/bona_file_server.py
solent/draft/console_demo.py
solent/draft/demonstrate_line_console.py
solent/draft/gollop_box.py
solent/draft/gruel_client_sandbox.py
solent/draft/gruel_server_sandbox.py
solent/draft/mountain_box.py
solent/draft/oled_ui_demo.py
solent/draft/redis_client.py
solent/draft/sdl.py
solent/draft/turn_based_game.py
solent/draft/winsnake.py
solent/draft/wrap_c_code.py
solent/draft/turnlib/__init__.py
solent/draft/turnlib/algobunny_mind.py
solent/draft/turnlib/cursor.py
solent/draft/turnlib/fabric.py
solent/draft/turnlib/glyph.py
solent/draft/turnlib/initiative.py
solent/draft/turnlib/logbook.py
solent/draft/turnlib/meep.py
solent/draft/turnlib/menu.py
solent/draft/turnlib/mind.py
solent/draft/turnlib/player_mind.py
solent/draft/turnlib/rogue_interaction.py
solent/draft/turnlib/rogue_plane.py
solent/draft/turnlib/scope.py
solent/eng/__init__.py
solent/eng/action_pool.py
solent/eng/activity.py
solent/eng/clock.py
solent/eng/cs.py
solent/eng/engine.py
solent/eng/ip_validator.py
solent/eng/metasock.py
solent/eng/nearcast_schema.py
solent/eng/orb.py
solent/eng/profile_event_loop.py
solent/eng/test_bridge_class_cog.py
solent/gruel/__init__.py
solent/gruel/gruel_press.py
