Metadata-Version: 1.1
Name: solent
Version: 0.49
Summary: Toolkit for creating message-driven systems
Home-page: https://github.com/solent-eng/solent
Author: UNKNOWN
Author-email: UNKNOWN
License: UNKNOWN
Download-URL: https://github.com/solent-eng/solent/tarball/0.49
Keywords: solent,eng,console,term,networking,async
Platform: UNKNOWN
